test_project/__init__.py
test_project/manage.py
test_project/runtests.py
test_project/settings.py
test_project/urls.py
test_project/polls/__init__.py
test_project/polls/admin.py
test_project/polls/models.py
test_project/polls/urls.py
test_project/polls/views.py
test_project/test_app/__init__.py
test_project/test_app/models.py
test_project/test_app/tests/__init__.py
test_project/test_app/tests/assertions_tests.py
test_project/test_app/tests/crawler_tests.py
test_project/test_app/tests/templatetags_tests.py
test_project/test_app/tests/testmaker_tests.py
test_project/test_app/tests/twill_tests.py
test_utils/__init__.py
test_utils/assertions.py
test_utils/mocks.py
test_utils/models.py
test_utils/urls.py
test_utils/views.py
test_utils/crawler/__init__.py
test_utils/crawler/base.py
test_utils/crawler/signals.py
test_utils/crawler/plugins/__init__.py
test_utils/crawler/plugins/base.py
test_utils/crawler/plugins/graph.py
test_utils/crawler/plugins/guppy_plugin.py
test_utils/crawler/plugins/memory_plugin.py
test_utils/crawler/plugins/pdb.py
test_utils/crawler/plugins/query_count.py
test_utils/crawler/plugins/sanitize.py
test_utils/crawler/plugins/tidy.py
test_utils/crawler/plugins/time_plugin.py
test_utils/crawler/plugins/urlconf.py
test_utils/management/__init__.py
test_utils/management/commands/__init__.py
test_utils/management/commands/crawlurls.py
test_utils/management/commands/makefixture.py
test_utils/management/commands/quicktest.py
test_utils/management/commands/relational_dumpdata.py
test_utils/management/commands/testmaker.py
test_utils/management/commands/testshell.py
test_utils/templatetags/__init__.py
test_utils/test_runners/__init__.py
test_utils/test_runners/keep_database.py
test_utils/test_runners/profile.py
test_utils/testmaker/__init__.py
test_utils/testmaker/replay.py
test_utils/testmaker/middleware/__init__.py
test_utils/testmaker/middleware/testmaker.py
test_utils/testmaker/processors/__init__.py
test_utils/testmaker/processors/base.py
django_test_utils3-1.1.11.dist-info/AUTHORS
django_test_utils3-1.1.11.dist-info/LICENSE
django_test_utils3-1.1.11.dist-info/METADATA
django_test_utils3-1.1.11.dist-info/WHEEL
django_test_utils3-1.1.11.dist-info/top_level.txt
django_test_utils3-1.1.11.dist-info/RECORD
