Metadata-Version: 2.1
Name: django-test-utils3
Version: 1.1.11
Summary: A package to help testing in Django
Home-page: https://github.com/phroiland/django-test-utils
Author: Johan Michaelson Phroiland
Author-email: jon@crowdkeep.com
License: UNKNOWN
Download-URL: https://github.com/phroiland/django-test-utils
Platform: UNKNOWN
Requires-Dist: BeautifulSoup4
Requires-Dist: twill3
Requires-Dist: django
Requires-Dist: six
